zndraw/.gitignore
zndraw/__init__.py
zndraw/_version.py
zndraw/analytics.py
zndraw/api_manager.py
zndraw/auth.py
zndraw/bookmarks_manager.py
zndraw/cli.py
zndraw/cli_entry.py
zndraw/config.py
zndraw/connectivity.py
zndraw/exceptions.py
zndraw/figures_manager.py
zndraw/frame_cache.py
zndraw/job.py
zndraw/job_executor.py
zndraw/lock.py
zndraw/materials.py
zndraw/metadata_manager.py
zndraw/msgpack_utils.py
zndraw/room_templates.py
zndraw/scene_manager.py
zndraw/screenshot_manager.py
zndraw/server.py
zndraw/server_manager.py
zndraw/session_manager.py
zndraw/settings.py
zndraw/socket_manager.py
zndraw/start_celery.py
zndraw/transformations.py
zndraw/version_utils.py
zndraw/zndraw.py
zndraw/app/__init__.py
zndraw/app/bookmark_routes.py
zndraw/app/chat_utils.py
zndraw/app/constants.py
zndraw/app/events.py
zndraw/app/extension_routes.py
zndraw/app/extension_utils.py
zndraw/app/file_browser.py
zndraw/app/filesystem_routes.py
zndraw/app/frame_index_manager.py
zndraw/app/frame_routes.py
zndraw/app/geometry_routes.py
zndraw/app/job_dispatcher.py
zndraw/app/job_manager.py
zndraw/app/job_routes.py
zndraw/app/lock_routes.py
zndraw/app/make_celery.py
zndraw/app/metadata_manager.py
zndraw/app/models.py
zndraw/app/redis_keys.py
zndraw/app/room_data_fetcher.py
zndraw/app/room_manager.py
zndraw/app/room_routes.py
zndraw/app/route_utils.py
zndraw/app/screenshot_chat_routes.py
zndraw/app/session_routes.py
zndraw/app/tasks.py
zndraw/app/utility_routes.py
zndraw/app/worker_routes.py
zndraw/app/worker_stats.py
zndraw/extensions/__init__.py
zndraw/extensions/abc.py
zndraw/extensions/analysis.py
zndraw/extensions/modifiers.py
zndraw/extensions/molecule_building.py
zndraw/extensions/selections.py
zndraw/generated/config.json
zndraw/geometries/__init__.py
zndraw/geometries/arrow.py
zndraw/geometries/base.py
zndraw/geometries/bonds.py
zndraw/geometries/box.py
zndraw/geometries/camera.py
zndraw/geometries/cell.py
zndraw/geometries/curve.py
zndraw/geometries/floor.py
zndraw/geometries/plane.py
zndraw-0.6.0.dist-info/METADATA
zndraw-0.6.0.dist-info/WHEEL
zndraw-0.6.0.dist-info/entry_points.txt
zndraw-0.6.0.dist-info/licenses/LICENSE
zndraw-0.6.0.dist-info/RECORD
