Metadata-Version: 2.4
Name: zndraw
Version: 0.6.0
Summary: ZnDraw
Project-URL: Repository, https://github.com/zincware/ZnDraw
Project-URL: Releases, https://github.com/zincware/ZnDraw/releases
Project-URL: Discord, https://discord.gg/7ncfwhsnm4
Project-URL: Documentation, https://zndraw.readthedocs.io/
Author: Paul Hohenberger
Author-email: Fabian Zills <fzills@icp.uni-stuttgart.de>, Rokas Elijošius <re344@cam.ac.uk>
License: Eclipse Public License - v 2.0
License-File: LICENSE
Requires-Python: >=3.11
Requires-Dist: argon2-cffi>=25.1.0
Requires-Dist: ase>=3.26.0
Requires-Dist: asebytes>=0.1.7
Requires-Dist: cachetools>=6.2.0
Requires-Dist: celery>=5.5.3
Requires-Dist: dnspython>=2.8.0
Requires-Dist: eventlet>=0.40.3
Requires-Dist: flask-socketio>=5.5.1
Requires-Dist: flask>=3.1.2
Requires-Dist: fsspec>=2025.10.0
Requires-Dist: lmdb>=1.7.5
Requires-Dist: msgpack-numpy>=0.4.8
Requires-Dist: msgpack>=1.1.1
Requires-Dist: networkx>=3.5
Requires-Dist: pandas>=2.3.3
Requires-Dist: plotly>=6.3.1
Requires-Dist: prometheus-client>=0.23.1
Requires-Dist: pydantic-settings>=2.8.0
Requires-Dist: pydantic>=2.11.9
Requires-Dist: pyjwt>=2.10.1
Requires-Dist: pymongo>=4.10.0
Requires-Dist: python-socketio[client]>=5.13.0
Requires-Dist: redis>=6.4.0
Requires-Dist: rich>=14.1.0
Requires-Dist: splines>=0.3.3
Requires-Dist: tqdm>=4.67.1
Requires-Dist: typer>=0.19.2
Requires-Dist: vesin>=0.3.8
Requires-Dist: znh5md>=0.4.8
Requires-Dist: znsocket>=0.3.0
Provides-Extra: full
Requires-Dist: molify>=0.2.1; extra == 'full'
